bamr/__init__.py
bamr/bamr.py
bamr-0.2.0.dist-info/LICENSE
bamr-0.2.0.dist-info/METADATA
bamr-0.2.0.dist-info/WHEEL
bamr-0.2.0.dist-info/top_level.txt
bamr-0.2.0.dist-info/RECORD
